cycquery/__init__.py
cycquery/base.py
cycquery/eicu.py
cycquery/gemini.py
cycquery/interface.py
cycquery/mimiciii.py
cycquery/mimiciv.py
cycquery/omop.py
cycquery/ops.py
cycquery/orm.py
cycquery/post_process/__init__.py
cycquery/post_process/gemini.py
cycquery/post_process/mimiciv.py
cycquery/post_process/util.py
cycquery/util.py
cycquery/utils/__init__.py
cycquery/utils/common.py
cycquery/utils/file.py
cycquery/utils/log.py
cycquery/utils/profile.py
cycquery-0.1.8.dist-info/LICENSE.md
cycquery-0.1.8.dist-info/METADATA
cycquery-0.1.8.dist-info/WHEEL
cycquery-0.1.8.dist-info/RECORD
