Metadata-Version: 2.3
Name: cycquery
Version: 0.1.8
Summary: A tool to query EHR databases
License: Apache-2.0
Author: Vector AI Engineering
Author-email: cyclops@vectorinstitute.ai
Requires-Python: >=3.9,<3.12
Classifier: License :: OSI Approved :: Apache Software License
Classifier: Programming Language :: Python :: 3
Classifier: Programming Language :: Python :: 3.9
Classifier: Programming Language :: Python :: 3.10
Classifier: Programming Language :: Python :: 3.11
Requires-Dist: SQLAlchemy (>=1.4.32,<2.0.0)
Requires-Dist: numpy (>=1.24.0,<2.0.0)
Requires-Dist: pandas (>2.0.0,<2.2.0)
Requires-Dist: psycopg2 (>=2.9.6,<3.0.0)
Requires-Dist: pyarrow (>=17.0.0,<18.0.0)
Project-URL: Documentation, https://vectorinstitute.github.io/cycquery/
Project-URL: Repository, https://github.com/VectorInstitute/cycquery
